diplomat/__init__.py
diplomat/__main__.py
diplomat/_cli_runner.py
diplomat/frontend_ops.py
diplomat/predictor_ops.py
diplomat/core_ops/__init__.py
diplomat/core_ops/shared_commands/__init__.py
diplomat/core_ops/shared_commands/annotate.py
diplomat/core_ops/shared_commands/save_from_restore.py
diplomat/core_ops/shared_commands/tracking.py
diplomat/core_ops/shared_commands/tweak.py
diplomat/core_ops/shared_commands/utils.py
diplomat/core_ops/shared_commands/visual_settings.py
diplomat/frontends/__init__.py
diplomat/frontends/deeplabcut/__init__.py
diplomat/frontends/deeplabcut/_verify_func.py
diplomat/frontends/deeplabcut/convert_tracks.py
diplomat/frontends/deeplabcut/dlc_importer.py
diplomat/frontends/deeplabcut/load_model.py
diplomat/frontends/sleap/__init__.py
diplomat/frontends/sleap/_verify_func.py
diplomat/frontends/sleap/convert_tracks.py
diplomat/frontends/sleap/load_model.py
diplomat/frontends/sleap/onnx_graph_builder.py
diplomat/frontends/sleap/run_utils.py
diplomat/frontends/sleap/sleap_imports.py
diplomat/frontends/sleap/sleap_providers.py
diplomat/predictors/__init__.py
diplomat/predictors/argmax.py
diplomat/predictors/fastplotter.py
diplomat/predictors/frame_exporter.py
diplomat/predictors/plotter.py
diplomat/predictors/fpe/__init__.py
diplomat/predictors/fpe/arr_utils.py
diplomat/predictors/fpe/fpe_help.py
diplomat/predictors/fpe/fpe_math.py
diplomat/predictors/fpe/fpe_test_data.py
diplomat/predictors/fpe/frame_pass.py
diplomat/predictors/fpe/frame_pass_loader.py
diplomat/predictors/fpe/skeleton_structures.py
diplomat/predictors/fpe/sparse_storage.py
diplomat/predictors/fpe/frame_passes/__init__.py
diplomat/predictors/fpe/frame_passes/cluster_frames.py
diplomat/predictors/fpe/frame_passes/create_skeleton.py
diplomat/predictors/fpe/frame_passes/fix_frame.py
diplomat/predictors/fpe/frame_passes/mit_viterbi.py
diplomat/predictors/fpe/frame_passes/optimize_std.py
diplomat/predictors/sfpe/__init__.py
diplomat/predictors/sfpe/assignment.py
diplomat_track-0.3.21.dist-info/licenses/AUTHORS
diplomat_track-0.3.21.dist-info/licenses/LICENSE
diplomat_track-0.3.21.dist-info/METADATA
diplomat_track-0.3.21.dist-info/WHEEL
diplomat_track-0.3.21.dist-info/entry_points.txt
diplomat_track-0.3.21.dist-info/top_level.txt
diplomat_track-0.3.21.dist-info/RECORD
