Metadata-Version: 2.4
Name: diplomat-track
Version: 0.3.21
Summary: Deep learning-based Identity Preserving Labeled-Object Multi-Animal Tracking.
Home-page: https://diplomattrack.org
Author: Isaac Robinson
Author-email: isaac.k.robinson2000@gmail.com
Project-URL: Homepage, https://diplomattrack.org
Project-URL: Documentation, https://diplomat.readthedocs.io
Project-URL: Source, https://github.com/TravisWheelerLab/DIPLOMAT
Platform: any
Classifier: Development Status :: 4 - Beta
Classifier: Environment :: Console
Classifier: Intended Audience :: Developers
Classifier: Intended Audience :: Science/Research
Classifier: Programming Language :: Python :: 3
Classifier: Programming Language :: Python :: 3 :: Only
Classifier: Typing :: Typed
Requires-Python: >=3.8
License-File: LICENSE
License-File: AUTHORS
Requires-Dist: opencv-python-headless
Requires-Dist: matplotlib
Requires-Dist: typing_extensions>=3.8
Requires-Dist: tqdm
Requires-Dist: PyYAML
Requires-Dist: pandas
Requires-Dist: numpy
Requires-Dist: numba
Provides-Extra: gui
Requires-Dist: wxpython; extra == "gui"
Provides-Extra: sleap
Requires-Dist: h5py; extra == "sleap"
Requires-Dist: tables; extra == "sleap"
Requires-Dist: tensorflow; extra == "sleap"
Requires-Dist: tf2onnx>=1.16.1; extra == "sleap"
Requires-Dist: onnx; extra == "sleap"
Requires-Dist: onnxruntime>=1.19; extra == "sleap"
Provides-Extra: sleap-nvidia
Requires-Dist: h5py; extra == "sleap-nvidia"
Requires-Dist: tables; extra == "sleap-nvidia"
Requires-Dist: tensorflow; extra == "sleap-nvidia"
Requires-Dist: tf2onnx>=1.16.1; extra == "sleap-nvidia"
Requires-Dist: onnx; extra == "sleap-nvidia"
Requires-Dist: onnxruntime-gpu>=1.19; extra == "sleap-nvidia"
Requires-Dist: nvidia-cuda-nvrtc-cu12~=12.0; extra == "sleap-nvidia"
Requires-Dist: nvidia-cuda-runtime-cu12~=12.0; extra == "sleap-nvidia"
Requires-Dist: nvidia-cufft-cu12~=11.0; extra == "sleap-nvidia"
Requires-Dist: nvidia-curand-cu12~=10.0; extra == "sleap-nvidia"
Requires-Dist: nvidia-cudnn-cu12~=9.0; extra == "sleap-nvidia"
Provides-Extra: dlc
Requires-Dist: h5py; extra == "dlc"
Requires-Dist: tables; extra == "dlc"
Requires-Dist: tensorflow; extra == "dlc"
Requires-Dist: tf2onnx>=1.16.1; extra == "dlc"
Requires-Dist: onnx; extra == "dlc"
Requires-Dist: onnxruntime>=1.19; extra == "dlc"
Provides-Extra: dlc-nvidia
Requires-Dist: h5py; extra == "dlc-nvidia"
Requires-Dist: tables; extra == "dlc-nvidia"
Requires-Dist: tensorflow; extra == "dlc-nvidia"
Requires-Dist: tf2onnx>=1.16.1; extra == "dlc-nvidia"
Requires-Dist: onnx; extra == "dlc-nvidia"
Requires-Dist: onnxruntime-gpu>=1.19; extra == "dlc-nvidia"
Requires-Dist: nvidia-cuda-nvrtc-cu12~=12.0; extra == "dlc-nvidia"
Requires-Dist: nvidia-cuda-runtime-cu12~=12.0; extra == "dlc-nvidia"
Requires-Dist: nvidia-cufft-cu12~=11.0; extra == "dlc-nvidia"
Requires-Dist: nvidia-curand-cu12~=10.0; extra == "dlc-nvidia"
Requires-Dist: nvidia-cudnn-cu12~=9.0; extra == "dlc-nvidia"
Provides-Extra: all
Requires-Dist: wxpython; extra == "all"
Requires-Dist: h5py; extra == "all"
Requires-Dist: tables; extra == "all"
Requires-Dist: tensorflow; extra == "all"
Requires-Dist: tf2onnx>=1.16.1; extra == "all"
Requires-Dist: onnx; extra == "all"
Requires-Dist: onnxruntime>=1.19; extra == "all"
Provides-Extra: all-nvidia
Requires-Dist: wxpython; extra == "all-nvidia"
Requires-Dist: h5py; extra == "all-nvidia"
Requires-Dist: tables; extra == "all-nvidia"
Requires-Dist: tensorflow; extra == "all-nvidia"
Requires-Dist: tf2onnx>=1.16.1; extra == "all-nvidia"
Requires-Dist: onnx; extra == "all-nvidia"
Requires-Dist: onnxruntime-gpu>=1.19; extra == "all-nvidia"
Requires-Dist: nvidia-cuda-nvrtc-cu12~=12.0; extra == "all-nvidia"
Requires-Dist: nvidia-cuda-runtime-cu12~=12.0; extra == "all-nvidia"
Requires-Dist: nvidia-cufft-cu12~=11.0; extra == "all-nvidia"
Requires-Dist: nvidia-curand-cu12~=10.0; extra == "all-nvidia"
Requires-Dist: nvidia-cudnn-cu12~=9.0; extra == "all-nvidia"
Provides-Extra: test
Requires-Dist: pytest; extra == "test"
Requires-Dist: scipy; extra == "test"
Dynamic: author
Dynamic: author-email
Dynamic: classifier
Dynamic: description
Dynamic: description-content-type
Dynamic: home-page
Dynamic: license-file
Dynamic: platform
Dynamic: project-url
Dynamic: provides-extra
Dynamic: requires-dist
Dynamic: requires-python
Dynamic: summary
